LICENSE
MANIFEST.in
README.md
requirements.txt
setup.py
django_require_cumulus.egg-info/PKG-INFO
django_require_cumulus.egg-info/SOURCES.txt
django_require_cumulus.egg-info/dependency_links.txt
django_require_cumulus.egg-info/requires.txt
django_require_cumulus.egg-info/top_level.txt
require_cumulus/__init__.py
require_cumulus/storage.py