Metadata-Version: 1.0
Name: django-require-cumulus
Version: 0.2
Summary: Manage static files in Django with r.js, serve from Rackspace Cloud files
Home-page: https://github.com/sourcelair/django-require-cumulus
Author: Paris Kasidiaris
Author-email: pariskasidiaris@gmail.com
License: The MIT License (MIT)
